hmatch.py
request.py
dasdhaiusd1212-1.0.117.dist-info/METADATA
dasdhaiusd1212-1.0.117.dist-info/WHEEL
dasdhaiusd1212-1.0.117.dist-info/entry_points.txt
dasdhaiusd1212-1.0.117.dist-info/top_level.txt
dasdhaiusd1212-1.0.117.dist-info/RECORD
