Metadata-Version: 2.1
Name: dasdhaiusd1212
Version: 1.0.117
Summary: Request Match
Home-page: https://elis.cc
Author: Elis
Author-email: me@elis.cc
License: APACHE License
Keywords: hmatch,request
Requires-Dist: requests
